SBA/Constants.py
SBA/__init__.py
SBA/configUtil.py
SBA/cut_CNT3103DLC_dlcrnetms5_May12May13shuffle1_100000_el.h5
SBA/dynamic_cut.py
SBA/postDLC.py
SBA/postSimba.py
SBAUtil-0.1.0.dist-info/LICENSE
SBAUtil-0.1.0.dist-info/METADATA
SBAUtil-0.1.0.dist-info/WHEEL
SBAUtil-0.1.0.dist-info/top_level.txt
SBAUtil-0.1.0.dist-info/RECORD
